dmtestutils/__init__.py
dmtestutils/comparisons.py
dmtestutils/fixtures.py
dmtestutils/frontend.py
dmtestutils/login.py
dmtestutils/mocking.py
dmtestutils/api_model_stubs/__init__.py
dmtestutils/api_model_stubs/audit_event.py
dmtestutils/api_model_stubs/base.py
dmtestutils/api_model_stubs/brief.py
dmtestutils/api_model_stubs/brief_response.py
dmtestutils/api_model_stubs/framework.py
dmtestutils/api_model_stubs/framework_agreement.py
dmtestutils/api_model_stubs/lot.py
dmtestutils/api_model_stubs/services.py
dmtestutils/api_model_stubs/supplier.py
dmtestutils/api_model_stubs/supplier_framework.py
digitalmarketplace_test_utils-3.0.0.dist-info/LICENCE
digitalmarketplace_test_utils-3.0.0.dist-info/METADATA
digitalmarketplace_test_utils-3.0.0.dist-info/WHEEL
digitalmarketplace_test_utils-3.0.0.dist-info/entry_points.txt
digitalmarketplace_test_utils-3.0.0.dist-info/top_level.txt
digitalmarketplace_test_utils-3.0.0.dist-info/RECORD
