Metadata-Version: 2.1
Name: digitalmarketplace-test-utils
Version: 3.0.0
Summary: Utilities for testing Digital Marketplace apps.
Home-page: https://github.com/alphagov/digitalmarketplace-test-utils
Author: GDS Developers
License: MIT
Platform: UNKNOWN
Requires-Python: ~=3.8
